JK_flip_flop/JK_flip_flop.v
module JK_FF(Q, Qbar, J, K, clk);
  input J, K, clk;
  output Q, Qbar;
  wire w1, w2;

  nand(w1, J, clk, Qbar);  // J input control
  nand(w2, K, clk, Q);     // K input control
  nand(Q, w1, Qbar);       // Final Q output
  nand(Qbar, w2, Q);       // Final Qbar output

endmodule

JK_flip_flop/JK_flip_flop_tb.v
module JK_FF_tb;
  reg J, K, clk;
  wire Q, Qbar;

  // Instantiate the JK Flip-Flop
  JK_FF uut (Q, Qbar, J, K, clk);

  // Generate Clock Signal (5-time unit period)
  always #5 clk = ~clk;  

  initial begin
    // Monitor output
    $monitor("Time=%0t | J=%b K=%b CLK=%b | Q=%b Qbar=%b", 
              $time, J, K, clk, Q, Qbar);

    // Initialize signals
    clk = 1; 
    J = 0; K = 0; #10;  // Hold State
    J = 0; K = 1; #10;  // Reset State (Q = 0, Qbar = 1)
    J = 1; K = 0; #10;  // Set State (Q = 1, Qbar = 0)
    J = 1; K = 1; #10;  // Toggle State (Q ⇄ Qbar)
    
    $finish;
  end
endmodule

JK_flip_flop/jk_flipflop.vcd
$date
	Mon Mar 10 12:20:41 2025
$end
$version
	Icarus Verilog
$end
$timescale
	1s
$end
$scope module JK_FF_tb $end
$var wire 1 ! Qbar $end
$var wire 1 " Q $end
$var reg 1 # J $end
$var reg 1 $ K $end
$var reg 1 % clk $end
$scope module uut $end
$var wire 1 # J $end
$var wire 1 $ K $end
$var wire 1 " Q $end
$var wire 1 ! Qbar $end
$var wire 1 % clk $end
$var wire 1 & w1 $end
$var wire 1 ' w2 $end
$upscope $end
$upscope $end
$enddefinitions $end
$comment Show the parameter values. $end
$dumpall
$end
#0
$dumpvars
1'
1&
0%
0$
0#
x"
x!
$end
#5
1%
#10
0%
1$
#15
x'
1%
#20
1'
0%
0$
1#
#25
x&
1%
#30
1&
0%
1$
#35
x&
x'
1%
#40
1&
1'
0%
